regex.py
replace.py
slug.py
github_slugger-0.0.2.dist-info/LICENSE
github_slugger-0.0.2.dist-info/METADATA
github_slugger-0.0.2.dist-info/WHEEL
github_slugger-0.0.2.dist-info/top_level.txt
github_slugger-0.0.2.dist-info/RECORD
