Metadata-Version: 2.1
Name: github_slugger
Version: 0.0.2
Summary: Generate a slug just like GitHub does for markdown headings. (JavaScript Port)
Author-email: Dan Flettre <flettre@gmail.com>, Titus Wormer <tituswormer@gmail.com>, Martin Heidegger <martin.heidegger@gmail.comn>
License: Copyright (c) 2015, Dan Flettre <fletd01@yahoo.com>
Project-URL: Homepage, https://github.com/martinheidegger/github_slugger
Project-URL: Bug Tracker, https://github.com/martinheidegger/github_slugger/issues
Keywords: slug,heading,processor
Classifier: Development Status :: 4 - Beta
Classifier: Topic :: Text Processing :: General
Classifier: Topic :: Utilities
Classifier: License :: OSI Approved :: ISC License (ISCL)
Classifier: Programming Language :: Python
Classifier: Programming Language :: Python :: 3
Requires-Python: >=3
License-File: LICENSE
